LICENSE
README.md
VERSION
setup.cfg
setup.py
es_logger/__init__.py
es_logger/cli.py
es_logger/interface.py
es_logger/zmq_client.py
es_logger.egg-info/PKG-INFO
es_logger.egg-info/SOURCES.txt
es_logger.egg-info/dependency_links.txt
es_logger.egg-info/entry_points.txt
es_logger.egg-info/not-zip-safe
es_logger.egg-info/requires.txt
es_logger.egg-info/top_level.txt
es_logger/plugins/__init__.py
es_logger/plugins/ansible.py
es_logger/plugins/artifact.py
es_logger/plugins/commit.py
es_logger/plugins/console_log_events.py
es_logger/plugins/junit.py
es_logger/plugins/stages.py
es_logger/plugins/target.py
test/test_ansible.py
test/test_artifact.py
test/test_cli.py
test/test_commit.py
test/test_console_log_events.py
test/test_es_logger.py
test/test_junit.py
test/test_plugins.py
test/test_stages.py
test/test_target.py
test/test_zmq_client.py