Metadata-Version: 2.1
Name: es-logger
Version: 6.2
Summary: Framework for Creating Logstash events from Jenkins Jobs
Home-page: https://github.com/CiscoDevNet/es-logger
Author: JP Sullivan (j3p0uk)
Author-email: jonpsull@cisco.com
License: UNKNOWN
Project-URL: Bug Reports, https://github.com/CiscoDevNet/es-logger/issues
Project-URL: Source, https://github.com/CiscoDevNet/es-logger/
Keywords: jenkins development elasticsearch logstash build
Platform: Any
Classifier: Development Status :: 4 - Beta
Classifier: Environment :: Console
Classifier: Intended Audience :: Developers
Classifier: Topic :: Software Development :: Build Tools
Classifier: Topic :: Software Development :: Testing
Classifier: License :: OSI Approved :: MIT License
Classifier: Programming Language :: Python :: 3
Classifier: Programming Language :: Python :: 3.7
Provides: es_logger
Provides: zmq_es_logger
